brandpy/__init__.py
brandpy/bw_api_caller.py
brandpy/bw_api_helper.py
brandpy/bw_auth_config.py
brandpy-0.0.9.dist-info/METADATA
brandpy-0.0.9.dist-info/WHEEL
brandpy-0.0.9.dist-info/entry_points.txt
brandpy-0.0.9.dist-info/licenses/LICENSE.txt
brandpy-0.0.9.dist-info/RECORD
