Metadata-Version: 2.1
Name: brandpy
Version: 0.0.9
Summary: This is a simple python wrapper for lookup calls of Brandwatch API.
Project-URL: Documentation, https://github.com/deamonpog/BrandPy#readme
Project-URL: Issues, https://github.com/deamonpog/BrandPy/issues
Project-URL: Source, https://github.com/deamonpog/BrandPy
Author-email: deamonpog <pog666@gmail.com>
License-Expression: MIT
License-File: LICENSE.txt
Classifier: Development Status :: 4 - Beta
Classifier: Programming Language :: Python
Classifier: Programming Language :: Python :: 3.7
Classifier: Programming Language :: Python :: 3.8
Classifier: Programming Language :: Python :: 3.9
Classifier: Programming Language :: Python :: 3.10
Classifier: Programming Language :: Python :: 3.11
Classifier: Programming Language :: Python :: Implementation :: CPython
Classifier: Programming Language :: Python :: Implementation :: PyPy
Requires-Python: >=3.7
Requires-Dist: numpy
Requires-Dist: pandas
Requires-Dist: pysimplegui
Requires-Dist: requests
Provides-Extra: gui
Requires-Dist: pysimplegui; extra == 'gui'
